pytest_crayons/__init__.py
pytest_crayons/plugin.py
pytest_crayons-0.0.9.dist-info/METADATA
pytest_crayons-0.0.9.dist-info/WHEEL
pytest_crayons-0.0.9.dist-info/entry_points.txt
pytest_crayons-0.0.9.dist-info/licenses/LICENSE
pytest_crayons-0.0.9.dist-info/RECORD
