Metadata-Version: 2.4
Name: pytest-crayons
Version: 0.0.9
Summary: A pytest plugin for colorful print statements
Project-URL: Home, https://github.com/okken/pytest-crayons
Author: Brian Okken
License: The MIT License (MIT)
License-File: LICENSE
Classifier: Development Status :: 5 - Production/Stable
Classifier: Framework :: Pytest
Classifier: Intended Audience :: Developers
Classifier: License :: OSI Approved :: MIT License
Classifier: Programming Language :: Python :: 3.9
Classifier: Programming Language :: Python :: 3.10
Classifier: Programming Language :: Python :: 3.11
Classifier: Programming Language :: Python :: 3.12
Classifier: Programming Language :: Python :: 3.13
Classifier: Programming Language :: Python :: 3.14
Classifier: Programming Language :: Python :: Free Threading
Classifier: Programming Language :: Python :: Free Threading :: 3 - Stable
Classifier: Topic :: Software Development :: Testing
Classifier: Topic :: Utilities
Requires-Python: >=3.9
Requires-Dist: pytest
